LICENSE.txt
MANIFEST.in
README.md
setup.cfg
setup.py
svox/__init__.py
svox/svox.py
svox_np.egg-info/PKG-INFO
svox_np.egg-info/SOURCES.txt
svox_np.egg-info/dependency_links.txt
svox_np.egg-info/top_level.txt
test/test_64.py
test/test_backward.py
test/test_basic.py
test/test_child.py
test/test_indexer.py
test/test_pad.py
test/test_push.py
test/test_simple.py